pyfe3d/__init__.py
pyfe3d/beamc.cpython-38-darwin.so
pyfe3d/beamc.pyx
pyfe3d/beamlr.cpython-38-darwin.so
pyfe3d/beamlr.pyx
pyfe3d/beamprop.cpython-38-darwin.so
pyfe3d/beamprop.pxd
pyfe3d/beamprop.pyx
pyfe3d/quad4.cpython-38-darwin.so
pyfe3d/quad4.pyx
pyfe3d/quad4r.cpython-38-darwin.so
pyfe3d/quad4r.pyx
pyfe3d/shellprop.cpython-38-darwin.so
pyfe3d/shellprop.pxd
pyfe3d/shellprop.pyx
pyfe3d/shellprop_utils.py
pyfe3d/spring.cpython-38-darwin.so
pyfe3d/spring.pyx
pyfe3d/tria3r.cpython-38-darwin.so
pyfe3d/tria3r.pyx
pyfe3d/truss.cpython-38-darwin.so
pyfe3d/truss.pyx
pyfe3d/version.py
pyfe3d-0.6.2.data/data/AUTHORS
pyfe3d-0.6.2.data/data/LICENSE
pyfe3d-0.6.2.data/data/README.md
pyfe3d-0.6.2.dist-info/AUTHORS
pyfe3d-0.6.2.dist-info/LICENSE
pyfe3d-0.6.2.dist-info/METADATA
pyfe3d-0.6.2.dist-info/WHEEL
pyfe3d-0.6.2.dist-info/top_level.txt
pyfe3d-0.6.2.dist-info/RECORD
