Metadata-Version: 2.1
Name: pyfe3d
Version: 0.6.2
Summary: General-purpose finite element solver for structural analysis and optimization based on Python and Cython
Home-page: https://github.com/saullocastro/pyfe3d
Author: Saullo G. P. Castro
Author-email: S.G.P.Castro@tudelft.nl
License: 3-Clause BSD
Keywords: finite elements,structural analysis,structural optimization,static analysis,buckling,vibration,panel flutter,structural dynamics,implicit time integration,explicit time integration
Classifier: Development Status :: 4 - Beta
Classifier: Intended Audience :: Education
Classifier: Intended Audience :: Science/Research
Classifier: Intended Audience :: Developers
Classifier: Intended Audience :: End Users/Desktop
Classifier: Topic :: Scientific/Engineering
Classifier: Topic :: Scientific/Engineering :: Mathematics
Classifier: Topic :: Education
Classifier: Topic :: Software Development
Classifier: Topic :: Software Development :: Libraries :: Python Modules
Classifier: Operating System :: POSIX :: BSD
Classifier: Operating System :: Microsoft :: Windows
Classifier: Operating System :: Unix
Classifier: Programming Language :: Python :: 3.8
Classifier: Programming Language :: Python :: 3.9
Classifier: Programming Language :: Python :: 3.10
Classifier: Programming Language :: Python :: 3.11
Classifier: Programming Language :: Python :: 3.12
Classifier: Programming Language :: Python :: 3.13
Classifier: License :: OSI Approved :: BSD License
Requires-Python: >=3.8
License-File: LICENSE
License-File: AUTHORS
